handshakes/H_slave.v
module Handshake_slave(
 input clk,
 input rst, 
 input valid, 
 input ready_in,
 input  wire [7:0] data_in,
 output reg ready_out
);
  reg reset =  0;
  reg  [7:0] data;

always @(posedge clk) begin
    if (rst)
        reset <= 1;
    else
    begin
        reset <= 0;
        ready_out <= ready_in;
    end
end

always @(*)begin
    if (reset)begin
        data = 0;
        ready_out = 0;
    end
    if (ready_out && valid)
        data = data_in;
    else
        data = data;
end   
endmodule

handshakes/H_master.v

module Handshake_master(
 input clk , rst , ready_inp,
 input   wire [7:0] data_in,
 output  reg [7:0] data,
 output  reg valid  
);
  reg reset = 0;
  reg dataChanged = 0;
  reg [7:0]  prevData ;

always @(posedge clk) begin
    if (rst)begin
        reset <= 1;
        data <= 0;
    end
    else
    begin
        reset <= 0;
        data <= data_in;
         if (data_in != data) begin
            dataChanged <= 1'b1;
      end else begin
            dataChanged <= 1'b0;
      end
      prevData <= data;
    end
    end

always @(*)begin
    if (reset)
        valid = 0;
    if (dataChanged)
        valid = 1;
        else
    if (ready_inp == 1 && dataChanged == 0)
        valid = 0 ;  
        else
        valid = valid;      
end 
endmodule

handshakes/H_testbench.v
`timescale 1ns / 1ps
`include"H_master.v"
`include"H_slave.v"

module H_tb;
    initial begin
        $dumpfile("H_testbench.vcd");
        $dumpvars(0,H_tb); 
    end

   reg clk;                 // Clock input
   reg rst;
   reg ready_input;
   reg [7:0] data_in;
   wire valid;
   wire [7:0]data;
   wire ready;

// Instantiate the uart module    
Handshake_master dut_Handshake_master (
    .clk(clk),
    .rst(rst),
    .data_in(data_in),
    .valid(valid),
    .ready_inp(ready),
    .data(data)
);

// Instantiate the uart module    
Handshake_slave  dut_Handshake_slave (
    .clk(clk),
    .rst(rst),
    .data_in(data),
    .valid(valid),
    .ready_out(ready),
    .ready_in(ready_input)
);


// Clock generation (20 MHz clock)
always begin
    #25 clk = ~clk;
end

// Testbench initialization
initial begin
    clk = 1;
    rst = 1;
    data_in = 8'hxx;
    ready_input = 0;
    #77
    rst = 0;
    data_in = 8'h6B;
    ready_input = 0;
    #100
     ready_input = 1;
     #50
     ready_input = 0;
      data_in = 8'h00;
      ready_input = 1;
      #100
       data_in = 8'hcc;
       #100
       ready_input = 0;
       #500
      ready_input = 0;
      data_in = 8'h00;
      #300
      ready_input = 1;
      #30
      ready_input = 0;

    


    // End simulation
    #5000
    $finish;
end
    endmodule

handshakes/H_testbench.vcd
$date
	Thu Nov 30 23:04:35 2023
$end
$version
	Icarus Verilog
$end
$timescale
	1ps
$end
$scope module H_tb $end
$var wire 1 ! valid $end
$var wire 1 " ready $end
$var wire 8 # data [7:0] $end
$var reg 1 $ clk $end
$var reg 8 % data_in [7:0] $end
$var reg 1 & ready_input $end
$var reg 1 ' rst $end
$scope module dut_Handshake_master $end
$var wire 1 $ clk $end
$var wire 8 ( data_in [7:0] $end
$var wire 1 ' rst $end
$var wire 1 " ready_inp $end
$var reg 8 ) data [7:0] $end
$var reg 1 * dataChanged $end
$var reg 8 + prevData [7:0] $end
$var reg 1 , reset $end
$var reg 1 ! valid $end
$upscope $end
$scope module dut_Handshake_slave $end
$var wire 1 $ clk $end
$var wire 8 - data_in [7:0] $end
$var wire 1 & ready_in $end
$var wire 1 ' rst $end
$var wire 1 ! valid $end
$var reg 8 . data [7:0] $end
$var reg 1 " ready_out $end
$var reg 1 / reset $end
$upscope $end
$upscope $end
$enddefinitions $end
#0
$dumpvars
1/
b0 .
b0 -
1,
bx +
0*
b0 )
bx (
1'
0&
bx %
1$
b0 #
0"
0!
$end
#25000
0$
#50000
1$
#75000
0$
#77000
b1101011 %
b1101011 (
0'
#100000
1!
b0 +
1*
b1101011 #
b1101011 )
b1101011 -
0,
0/
1$
#125000
0$
#150000
b1101011 +
0*
1$
#175000
0$
#177000
1&
#200000
0!
b1101011 .
1"
1$
#225000
0$
#227000
b0 %
b0 (
1&
#250000
b0 .
1!
1*
b0 #
b0 )
b0 -
1$
#275000
0$
#300000
0!
b0 +
0*
1$
#325000
0$
#327000
b11001100 %
b11001100 (
#350000
b11001100 .
1!
1*
b11001100 #
b11001100 )
b11001100 -
1$
#375000
0$
#400000
0!
b11001100 +
0*
1$
#425000
0$
#427000
0&
#450000
0"
1$
#475000
0$
#500000
1$
#525000
0$
#550000
1$
#575000
0$
#600000
1$
#625000
0$
#650000
1$
#675000
0$
#700000
1$
#725000
0$
#750000
1$
#775000
0$
#800000
1$
#825000
0$
#850000
1$
#875000
0$
#900000
1$
#925000
0$
#927000
b0 %
b0 (
#950000
1!
1*
b0 #
b0 )
b0 -
1$
#975000
0$
#1000000
b0 +
0*
1$
#1025000
0$
#1050000
1$
#1075000
0$
#1100000
1$
#1125000
0$
#1150000
1$
#1175000
0$
#1200000
1$
#1225000
0$
#1227000
1&
#1250000
0!
b0 .
1"
1$
#1257000
0&
#1275000
0$
#1300000
0"
1$
