AXI4_Lite/AXI4_Lite_slave.v
module AXI4_Lite_slave(
 input clk , 
 input reset ,
// global_signals 

// write_address_channel_signals
 input  wire [31:0] awaddr_slave_input,
 input  wire awvalid_slave_input,
 output reg awready_slave_output,
 input  wire [2:0] awprot_slave_input,
 input  wire awready_slave_input,


// write_data_channel_signals
 input  wire [31:0] wdata_slave_input,
 input  wire wvalid_slave_input,
 output reg wready_slave_output,
 input  wire [3:0] wstrb_slave_input,
 input  wire wready_slave_input,


// write_response_channel_signals
 output   reg     bvalid_slave_output,
 input    wire    bready_slave_input,
 input    wire    [1:0] bresp_slave_input,
output    reg     [1:0] bresp_slave_output,

// read_address_channel_signals
 input  wire [31:0] araddr_slave_input,
 input  wire arvalid_slave_input,
 output reg arready_slave_output,
 input  wire [2:0] arprot_slave_input,
 input  wire arready_slave_input,


// read_data_channel_signals
 output   reg     rvalid_slave_output,
 input    wire    rready_slave_input,
 input    wire    [1:0] rresp_slave_input,
output    reg     [1:0] rresp_slave_output,
 output  reg   [31:0] rdata_slave_output,
 input  wire   [31:0] rdata_slave_input

);






 
 // write_address_channel_code
 reg rst = 0;
 reg [31:0] awaddr_save_reg = 0;
 reg [2:0]  awprot_save_reg = 3'bxxx;

 always @(posedge clk) begin
     if (reset == 0) begin
        rst <= 1;
        awready_slave_output = 0;
     end
     else
     begin
       rst <= 0;
        awready_slave_output <= awready_slave_input;
     end
    end

 always @(*)begin
    if (rst)begin
         awaddr_save_reg = 0;
         awprot_save_reg = 0;
        end
    if (awready_slave_output && awvalid_slave_input)begin
        awprot_save_reg = awprot_slave_input;
        awaddr_save_reg = awaddr_slave_input;  
    end
    else begin
        awaddr_save_reg = awaddr_save_reg;
        awprot_save_reg = awprot_save_reg;
    end
 end

// write_address_channel_code_ends







// write_data_channel_code_starts
 reg [31:0] wdata_save_reg = 0;
 reg [3:0]  wstrb_save_reg = 0;
reg  delay = 0 , delay1 = 0 , delay2 = 0;

  always @(posedge clk) begin
     if (reset == 0) begin
        wready_slave_output = 0;
        bresp_slave_output = 0;
     end
     else
     begin
        wready_slave_output <= wready_slave_input;
        bresp_slave_output <= bresp_slave_input;
     end
     if (bvalid_slave_output == 1)
      delay = 1; 
      else
      delay = 0;
    
      if (delay1 == 1)
      delay2 = 1; 
      else
      delay2 = 0;
end


 always @(*)begin
    if (rst)begin
         wdata_save_reg = 0;
         wstrb_save_reg = 0;
         bvalid_slave_output = 0; 
        end
    if (wready_slave_output && wvalid_slave_input)begin
         wstrb_save_reg = wstrb_slave_input;
         wdata_save_reg = wdata_slave_input;
         // write_data_channel_code_ends

         // write_dataresponse_channel_code_starts
         bvalid_slave_output = 1; 
    end
    else begin
        wdata_save_reg = wdata_save_reg;
        wstrb_save_reg = wstrb_save_reg;
    end

     if (delay == 1)
        delay1 = 1;
        else
        delay1 = 0; 
     
     if (delay2 == 1)
      bvalid_slave_output  = 0; 
      else
      bvalid_slave_output = bvalid_slave_output ; 

 end
 // write_response_channel_code_ends










 // write_address_channel_code
 reg [2:0]  arprot_save_reg = 3'bxxx;
reg  rdelay = 0 , rdelay1 = 0 , rdelay2 = 0;
reg [31:0] araddr_save_reg = 0 ;

 always @(posedge clk) begin
     if (reset == 0) begin
        arready_slave_output = 0;
        rresp_slave_output = 0;
        rdata_slave_output = 0;
     end
     else
     begin
        arready_slave_output <= arready_slave_input;
        rdata_slave_output <= rdata_slave_input;
        rresp_slave_output <= rresp_slave_input;
     end
      
     if (rvalid_slave_output == 1)
      rdelay = 1; 
      else
      rdelay = 0;
    
      if (rdelay1 == 1)
      rdelay2 = 1; 
      else
      rdelay2 = 0;
    end

 always @(*)begin
    if (rst)begin
         araddr_save_reg = 0;
         arprot_save_reg = 0;
         rvalid_slave_output = 0;
        end
    if (arready_slave_output && arvalid_slave_input)begin
        arprot_save_reg = arprot_slave_input;
        araddr_save_reg = araddr_slave_input;  
        rvalid_slave_output = 1;
    end
    else begin
        araddr_save_reg = araddr_save_reg;
        arprot_save_reg = arprot_save_reg;
    end
     if (rdelay == 1)
        rdelay1 = 1;
        else
        rdelay1 = 0; 
     
     if (rdelay2 == 1)
      rvalid_slave_output  = 0; 
      else
      rvalid_slave_output = rvalid_slave_output ; 

 end

// read_data_channel_code_ends
endmodule

AXI4_Lite/AXI4_Lite_master.v
module AXI4_Lite_master(
   // global_signals 
 input clk, 
 input reset,


 // write_address_channel_signals
 output  reg   [31:0] awaddr_master_output,
 output  reg   awvalid_master_output,
 input   wire  awready_master_input,
 input  wire   [31:0] awaddr_master_input,
 output  reg   [2:0] awprot_master_output,
 input  wire   [2:0] awprot_master_input,



 // write_data_channel_signals
 output  reg   [31:0] wdata_master_output,
 output  reg   wvalid_master_output,
 input   wire  wready_master_input,
 input  wire   [31:0] wdata_master_input,
 output  reg   [3:0] wstrb_master_output,
 input  wire   [3:0] wstrb_master_input,

 // write_response_channel_signals
 input   wire   bvalid_master_input,
 output  reg    bready_master_output,
 input   wire   [1:0] bresp_master_input,



 // read_address_channel_signals
 output  reg   [31:0] araddr_master_output,
 output  reg   arvalid_master_output,
 input   wire  arready_master_input,
 input  wire   [31:0] araddr_master_input,
 output  reg   [2:0] arprot_master_output,
 input  wire   [2:0] arprot_master_input,


 // read_data_channel_signals
 input   wire   rvalid_master_input,
 output  reg    rready_master_output,
 input   wire   [1:0] rresp_master_input,
input  wire   [31:0] rdata_master_input,
input wire rready_master_input

);


 // write_address_channel_code
 reg rst = 0;
 reg addressChanged = 0;

 always @(posedge clk) begin
     if (reset == 0)begin
        awaddr_master_output <= 32'h00000000;
        awprot_master_output <= 0;
        rst <= 1;
     end
     else
     begin
       rst = 0;
       awaddr_master_output <= awaddr_master_input;
       awprot_master_output <= awprot_master_input;
     end
       if (awaddr_master_output != awaddr_master_input)begin
           addressChanged <= 1'b1;
      end else begin
            addressChanged <= 1'b0;
      end
 end

 always @(*)begin
    if (rst)
        awvalid_master_output  = 0;
    if (addressChanged)begin
        awvalid_master_output  = 1;
    end
    else
    if (awready_master_input == 1 && addressChanged == 0)
        awvalid_master_output = 0;
    else
        awvalid_master_output = awvalid_master_output; 
 end
 
// write_address_channel_code_ends





// write_data_channel_code_starts
reg dataChanged = 0;
reg [1:0]  bresp_master_save_register = 0;

always @(posedge clk) begin
     if (reset == 0)begin
        wdata_master_output <= 32'h00000000;
        wstrb_master_output <= 0;
     end
     else
     begin
       wdata_master_output <= wdata_master_input;
       wstrb_master_output <= wstrb_master_input;
     end
       if (wdata_master_output != wdata_master_input)begin
           dataChanged <= 1'b1;
      end else begin
            dataChanged <= 1'b0;
      end
 end

 always @(*)begin
    bready_master_output = 1;
    if (rst)
        wvalid_master_output  = 0;
    if (dataChanged)begin
        wvalid_master_output  = 1;
    end
    else
    if (wready_master_input == 1 && dataChanged == 0)begin
        wvalid_master_output = 0;
        
    end
    else
        wvalid_master_output = wvalid_master_output; 

    if (bvalid_master_input && bready_master_output)begin
       bresp_master_save_register = bresp_master_input;
    end
    else begin
       bresp_master_save_register = bresp_master_save_register;
       bready_master_output = bready_master_output;  
    end
end
 // write_data_channel_code_ends
// write_response_channel_code_starts
// write_response_channel_code_ends




 // read_address_channel_code
 reg [31:0] rdata_master_save_register ;
 reg  [1:0] rresp_master_save_register ;
 reg read_addressChanged = 0;

 always @(posedge clk) begin
     if (reset == 0)begin
        araddr_master_output <= 32'h00000000;
        arprot_master_output <= 0;
        rready_master_output <=0;
     end
     else
     begin
        rready_master_output <= rready_master_input;
       araddr_master_output <= araddr_master_input;
       arprot_master_output <= arprot_master_input;
     end
       if (araddr_master_output != araddr_master_input)begin
           read_addressChanged <= 1'b1;
      end else begin
            read_addressChanged <= 1'b0;
      end
 end

 always @(*)begin
    if (rst)begin
        arvalid_master_output  = 0;
        rdata_master_save_register = 0;
        rresp_master_save_register = 0;
    end
    if (read_addressChanged)begin
        arvalid_master_output  = 1;
    end
    else
    if (arready_master_input == 1 && read_addressChanged == 0)
        arvalid_master_output = 0;
    else
        arvalid_master_output = arvalid_master_output; 

    if (rvalid_master_input == 1 && rready_master_output == 1) begin
        rdata_master_save_register = rdata_master_input;
        rresp_master_save_register = rresp_master_input;
    end
    else begin
       rdata_master_save_register = rdata_master_save_register; 
       rresp_master_save_register = rresp_master_save_register;
    end
 end
 
// read_address_channel_code_ends
endmodule

AXI4_Lite/AXI4_Lite_testbench.v
`timescale 1ns / 1ps
`include"AXI4_Lite_master.v"
`include"AXI4_Lite_slave.v"

module AXI4_Lite_tb;
    initial begin
        $dumpfile("AXI4_Lite_testbench.vcd");
        $dumpvars(0, AXI4_Lite_tb); 
    end

// registers used to pass the input in master and slave 
   reg clk;                 
   reg reset;
   //global signals  

   //write_address_registers 
   reg aready_input;
   reg [31:0] address_in;
   reg [2:0] awprot_in;


   // wire that connects the master and slave.
   // write_address_wires
   wire avalid;
   wire [31:0]address;
   wire aready;
   wire [2:0] awprot;

      //write_data_registers 
   reg dready_input;
   reg [31:0] data_in;
   reg [3:0] dwstrb_in;

   // write_data_wires
   wire dvalid;
   wire [31:0]data;
   wire dready;
   wire [3:0] dwstrb;


  //write_response_registers 
   reg [1:0] bresp_input;

   // write_response_wires
   wire rvalid;
   wire rready;
   wire [1:0] bresp;

    //write_address_registers 
   reg raready_input;
   reg [31:0] raddress_in;
   reg [2:0] raprot_in;


   // wire that connects the master and slave.
   // write_address_wires
   wire ravalid;
   wire [31:0]raddress;
   wire raready;
   wire [2:0] raprot;

    //read_response_registers 
   reg [1:0] rresp_input;
   reg [31:0] rdata_input;
   reg rready_input;


   // read_response_wires
   wire rrvalid;
   wire rrready;
   wire [1:0] rresp;
   wire [31:0] rdata;

   
   

// Instantiate the AXI4_Lite_master module    

AXI4_Lite_master dut_AXI4_Lite_master (
    .clk(clk),
    .reset(reset),
    // global signals 


     //write_address_signals_master_starts
    .awaddr_master_input(address_in),
    .awaddr_master_output(address),
    .awvalid_master_output(avalid),
    .awready_master_input(aready),
    .awprot_master_output(awprot),
    .awprot_master_input(awprot_in),
    // write_address_signals_master_ends

         //write_data_signals_master_starts
    .wdata_master_input(data_in),
    .wdata_master_output(data),
    .wvalid_master_output(dvalid),
    .wready_master_input(dready),
    .wstrb_master_output(dwstrb),
    .wstrb_master_input(dwstrb_in),
    // write_data_signals_master_ends

    // write_response_signals_master_starts
    .bvalid_master_input(rvalid),
    .bready_master_output(rready),
    .bresp_master_input(bresp),
    // write_response_signals_master_ends


    //read_address_signals_master_starts
    .araddr_master_input(raddress_in),
    .araddr_master_output(raddress),
    .arvalid_master_output(ravalid),
    .arready_master_input(raready),
    .arprot_master_output(raprot),
    .arprot_master_input(raprot_in),
    // read_address_signals_master_ends


       


 //read_data_signals_master_starts
    .rdata_master_input(rdata),
    .rresp_master_input(rresp),
    .rready_master_input(rready_input),
    .rready_master_output(rrready),
    .rvalid_master_input(rrvalid)
    // read_data_signals_master_ends


);

// Instantiate the AXI4_Lite_slave module    
AXI4_Lite_slave  dut_AXI4_Lite_slave (
    .clk(clk),
    .reset(reset),
    // global signals 

     //write_address_signals_slave_starts
    .awaddr_slave_input(address),
    .awvalid_slave_input(avalid),
    .awready_slave_output(aready),
    .awready_slave_input(aready_input),
    .awprot_slave_input(awprot),
    // write_address_signals_slave_ends

    //write_address_signals_slave_starts
    .wdata_slave_input(data),
    .wvalid_slave_input(dvalid),
    .wready_slave_output(dready),
    .wready_slave_input(dready_input),
    .wstrb_slave_input(dwstrb),
    // write_address_signals_slave_ends


    //write_response_signals_slave_starts
    .bresp_slave_input(bresp_input),
    .bresp_slave_output(bresp),
    .bready_slave_input(rready),
    .bvalid_slave_output(rvalid),
    // write_response_signals_slave_ends

    //write_address_signals_slave_starts
    .araddr_slave_input(raddress),
    .arvalid_slave_input(ravalid),
    .arready_slave_output(raready),
    .arready_slave_input(raready_input),
    .arprot_slave_input(raprot),
    // write_address_signals_slave_ends

       //read_data_signals_slave_starts
    .rdata_slave_input(rdata_input),
    .rdata_slave_output(rdata),
    .rresp_slave_input(rresp_input),
    .rresp_slave_output(rresp),
    .rready_slave_input(rrready),
    .rvalid_slave_output(rrvalid)
    // read_data_signals_slave_ends
);


// Clock generation (20 MHz clock)
always begin
    #25 clk = ~clk;
end

// Testbench initialization
initial begin
    clk = 1;
    reset = 0;
    address_in = 32'hxxxxxxxx;
    awprot_in = 3'b000;
   aready_input = 0;
    #200
    reset = 1;
    address_in = 32'h6BBBBBBB;
    awprot_in = 3'b111;
    #200
    aready_input = 1;
    #100
     aready_input = 0;
     #350
     aready_input = 0;
      address_in = 32'h10100111;
      awprot_in = 3'b000;
      aready_input = 0;
      #300
      aready_input = 1;
      #100
       aready_input = 0;
       #400
       address_in = 32'hCCCCCCCC;
       awprot_in = 3'b111;
       #200
       aready_input = 1;
       #100
      aready_input = 0;
    // End simulation
    #20000
    $finish;
end

   initial begin
    dready_input = 0;
    data_in = 0;
    bresp_input = 0;
    #2020
    data_in = 32'h6BBBBBBB;
    dwstrb_in = 4'b1111;
    dready_input = 0;
    bresp_input = 1;
    #500
     dready_input = 1;
     #100
     dready_input = 0;
     #400
    data_in = 32'h00000000;
    dwstrb_in = 4'b0000;
    dready_input = 0;
    #200
    dready_input = 1;
    #200
    dready_input = 0;
      #500
       data_in = 32'hCCCCCCCC;
       dwstrb_in = 4'b1111;
       #100
       dready_input = 1;
       #500
      dready_input = 0;
    // End simulation
    #20000
    $finish;
end
 


 initial begin
     raddress_in = 32'h00000000;
     raprot_in = 3'b000;
     raready_input = 0;
    #5000
    raprot_in = 3'b000;
   raready_input = 0;
    #577
    raddress_in = 32'h6BBBBBBB;
    raprot_in = 3'b111;
    #200
    raready_input = 1;
    #300
     raready_input = 0;
     #450
      raready_input = 0;
      raddress_in = 32'h00000000;
      raprot_in = 3'b000;
      raready_input = 0;
      #500
      raready_input = 1;
      #150
       raready_input = 0;
       #800
       raddress_in = 32'hCCCCCCCC;
       raprot_in = 3'b111;
       #300
       raready_input = 1;
       #500
      raready_input = 0;
    // End simulation
    #20000
    $finish;
 end


     initial begin
     rdata_input = 32'h00000000;
     rresp_input = 2'b00;
     rready_input = 1;
    #5000
     rresp_input = 2'b00;
   rready_input = 1;
    #577
    rdata_input = 32'h6BBBBBBB;
    rready_input = 2'b11;
    #200
    rready_input = 1;
    #300
     rready_input = 1;
     #450
      rready_input = 1;
      rdata_input = 32'h00000000;
      rresp_input = 2'b00;
      rready_input = 1;
      #500
      rready_input = 1;
      #150
       rready_input = 1;
       #800
       rdata_input = 32'hCCCCCCCC;
       rresp_input = 2'b11;
       #300
       rready_input = 1;
       #500
      rready_input = 1;
    // End simulation
    #20000
    $finish;
end
    endmodule

AXI4_Lite/AXI4_Lite_testbench.vcd
$date
	Tue Dec  5 15:53:12 2023
$end
$version
	Icarus Verilog
$end
$timescale
	1ps
$end
$scope module AXI4_Lite_tb $end
$var wire 1 ! rvalid $end
$var wire 1 " rrvalid $end
$var wire 1 # rrready $end
$var wire 2 $ rresp [1:0] $end
$var wire 1 % rready $end
$var wire 32 & rdata [31:0] $end
$var wire 1 ' ravalid $end
$var wire 1 ( raready $end
$var wire 3 ) raprot [2:0] $end
$var wire 32 * raddress [31:0] $end
$var wire 4 + dwstrb [3:0] $end
$var wire 1 , dvalid $end
$var wire 1 - dready $end
$var wire 32 . data [31:0] $end
$var wire 2 / bresp [1:0] $end
$var wire 3 0 awprot [2:0] $end
$var wire 1 1 avalid $end
$var wire 1 2 aready $end
$var wire 32 3 address [31:0] $end
$var reg 32 4 address_in [31:0] $end
$var reg 1 5 aready_input $end
$var reg 3 6 awprot_in [2:0] $end
$var reg 2 7 bresp_input [1:0] $end
$var reg 1 8 clk $end
$var reg 32 9 data_in [31:0] $end
$var reg 1 : dready_input $end
$var reg 4 ; dwstrb_in [3:0] $end
$var reg 32 < raddress_in [31:0] $end
$var reg 3 = raprot_in [2:0] $end
$var reg 1 > raready_input $end
$var reg 32 ? rdata_input [31:0] $end
$var reg 1 @ reset $end
$var reg 1 A rready_input $end
$var reg 2 B rresp_input [1:0] $end
$scope module dut_AXI4_Lite_master $end
$var wire 32 C araddr_master_input [31:0] $end
$var wire 3 D arprot_master_input [2:0] $end
$var wire 32 E awaddr_master_input [31:0] $end
$var wire 3 F awprot_master_input [2:0] $end
$var wire 1 8 clk $end
$var wire 1 @ reset $end
$var wire 1 A rready_master_input $end
$var wire 32 G wdata_master_input [31:0] $end
$var wire 4 H wstrb_master_input [3:0] $end
$var wire 1 - wready_master_input $end
$var wire 1 " rvalid_master_input $end
$var wire 2 I rresp_master_input [1:0] $end
$var wire 32 J rdata_master_input [31:0] $end
$var wire 1 ! bvalid_master_input $end
$var wire 2 K bresp_master_input [1:0] $end
$var wire 1 2 awready_master_input $end
$var wire 1 ( arready_master_input $end
$var reg 1 L addressChanged $end
$var reg 32 M araddr_master_output [31:0] $end
$var reg 3 N arprot_master_output [2:0] $end
$var reg 1 ' arvalid_master_output $end
$var reg 32 O awaddr_master_output [31:0] $end
$var reg 3 P awprot_master_output [2:0] $end
$var reg 1 1 awvalid_master_output $end
$var reg 1 % bready_master_output $end
$var reg 2 Q bresp_master_save_register [1:0] $end
$var reg 1 R dataChanged $end
$var reg 32 S rdata_master_save_register [31:0] $end
$var reg 1 T read_addressChanged $end
$var reg 1 # rready_master_output $end
$var reg 2 U rresp_master_save_register [1:0] $end
$var reg 1 V rst $end
$var reg 32 W wdata_master_output [31:0] $end
$var reg 4 X wstrb_master_output [3:0] $end
$var reg 1 , wvalid_master_output $end
$upscope $end
$scope module dut_AXI4_Lite_slave $end
$var wire 32 Y araddr_slave_input [31:0] $end
$var wire 3 Z arprot_slave_input [2:0] $end
$var wire 1 > arready_slave_input $end
$var wire 1 ' arvalid_slave_input $end
$var wire 32 [ awaddr_slave_input [31:0] $end
$var wire 3 \ awprot_slave_input [2:0] $end
$var wire 1 5 awready_slave_input $end
$var wire 1 1 awvalid_slave_input $end
$var wire 1 % bready_slave_input $end
$var wire 2 ] bresp_slave_input [1:0] $end
$var wire 1 8 clk $end
$var wire 32 ^ rdata_slave_input [31:0] $end
$var wire 1 @ reset $end
$var wire 1 # rready_slave_input $end
$var wire 2 _ rresp_slave_input [1:0] $end
$var wire 32 ` wdata_slave_input [31:0] $end
$var wire 1 : wready_slave_input $end
$var wire 4 a wstrb_slave_input [3:0] $end
$var wire 1 , wvalid_slave_input $end
$var reg 32 b araddr_save_reg [31:0] $end
$var reg 3 c arprot_save_reg [2:0] $end
$var reg 1 ( arready_slave_output $end
$var reg 32 d awaddr_save_reg [31:0] $end
$var reg 3 e awprot_save_reg [2:0] $end
$var reg 1 2 awready_slave_output $end
$var reg 2 f bresp_slave_output [1:0] $end
$var reg 1 ! bvalid_slave_output $end
$var reg 1 g delay $end
$var reg 1 h delay1 $end
$var reg 1 i delay2 $end
$var reg 32 j rdata_slave_output [31:0] $end
$var reg 1 k rdelay $end
$var reg 1 l rdelay1 $end
$var reg 1 m rdelay2 $end
$var reg 2 n rresp_slave_output [1:0] $end
$var reg 1 o rst $end
$var reg 1 " rvalid_slave_output $end
$var reg 32 p wdata_save_reg [31:0] $end
$var reg 1 - wready_slave_output $end
$var reg 4 q wstrb_save_reg [3:0] $end
$upscope $end
$upscope $end
$enddefinitions $end
#0
$dumpvars
b0 q
b0 p
1o
b0 n
0m
0l
0k
b0 j
0i
0h
0g
b0 f
b0 e
b0 d
b0 c
b0 b
b0 a
b0 `
b0 _
b0 ^
b0 ]
b0 \
b0 [
b0 Z
b0 Y
b0 X
b0 W
1V
b0 U
0T
b0 S
0R
b0 Q
b0 P
b0 O
b0 N
b0 M
0L
b0 K
b0 J
b0 I
bx H
b0 G
b0 F
bx E
b0 D
b0 C
b0 B
1A
0@
b0 ?
0>
b0 =
b0 <
bx ;
0:
b0 9
18
b0 7
b0 6
05
bx 4
b0 3
02
01
b0 0
b0 /
b0 .
0-
0,
b0 +
b0 *
b0 )
0(
0'
b0 &
1%
b0 $
0#
0"
0!
$end
#25000
08
#50000
18
#75000
08
#100000
18
#125000
08
#150000
18
#175000
08
#200000
11
1L
b111 0
b111 P
b111 \
b1101011101110111011101110111011 3
b1101011101110111011101110111011 O
b1101011101110111011101110111011 [
bx +
bx X
bx a
1#
0o
0V
18
b111 6
b111 F
b1101011101110111011101110111011 4
b1101011101110111011101110111011 E
1@
#225000
08
#250000
0L
18
#275000
08
#300000
18
#325000
08
#350000
18
#375000
08
#400000
01
b1101011101110111011101110111011 d
b111 e
12
18
15
#425000
08
#450000
18
#475000
08
#500000
02
18
05
#525000
08
#550000
18
#575000
08
#600000
18
#625000
08
#650000
18
#675000
08
#700000
18
#725000
08
#750000
18
#775000
08
#800000
18
#825000
08
#850000
11
1L
b0 0
b0 P
b0 \
b10000000100000000000100010001 3
b10000000100000000000100010001 O
b10000000100000000000100010001 [
18
b0 6
b0 F
b10000000100000000000100010001 4
b10000000100000000000100010001 E
#875000
08
#900000
0L
18
#925000
08
#950000
18
#975000
08
#1000000
18
#1025000
08
#1050000
18
#1075000
08
#1100000
18
#1125000
08
#1150000
01
b10000000100000000000100010001 d
b0 e
12
18
15
#1175000
08
#1200000
18
#1225000
08
#1250000
02
18
05
#1275000
08
#1300000
18
#1325000
08
#1350000
18
#1375000
08
#1400000
18
#1425000
08
#1450000
18
#1475000
08
#1500000
18
#1525000
08
#1550000
18
#1575000
08
#1600000
18
#1625000
08
#1650000
11
1L
b111 0
b111 P
b111 \
b11001100110011001100110011001100 3
b11001100110011001100110011001100 O
b11001100110011001100110011001100 [
18
b111 6
b111 F
b11001100110011001100110011001100 4
b11001100110011001100110011001100 E
#1675000
08
#1700000
0L
18
#1725000
08
#1750000
18
#1775000
08
#1800000
18
#1825000
08
#1850000
01
b11001100110011001100110011001100 d
b111 e
12
18
15
#1875000
08
#1900000
18
#1925000
08
#1950000
02
18
05
#1975000
08
#2000000
18
#2020000
b1 7
b1 ]
b1111 ;
b1111 H
b1101011101110111011101110111011 9
b1101011101110111011101110111011 G
#2025000
08
#2050000
1,
b1 /
b1 K
b1 f
1R
b1111 +
b1111 X
b1111 a
b1101011101110111011101110111011 .
b1101011101110111011101110111011 W
b1101011101110111011101110111011 `
18
#2075000
08
#2100000
0R
18
#2125000
08
#2150000
18
#2175000
08
#2200000
18
#2225000
08
#2250000
18
#2275000
08
#2300000
18
#2325000
08
#2350000
18
#2375000
08
#2400000
18
#2425000
08
#2450000
18
#2475000
08
#2500000
18
#2520000
1:
#2525000
08
#2550000
b1 Q
0,
1!
b1101011101110111011101110111011 p
b1111 q
1-
18
#2575000
08
#2600000
1h
1g
18
#2620000
0:
#2625000
08
#2650000
0-
0!
1i
18
#2675000
08
#2700000
0h
0g
18
#2725000
08
#2750000
0i
18
#2775000
08
#2800000
18
#2825000
08
#2850000
18
#2875000
08
#2900000
18
#2925000
08
#2950000
18
#2975000
08
#3000000
18
#3020000
b0 ;
b0 H
b0 9
b0 G
#3025000
08
#3050000
1,
1R
b0 +
b0 X
b0 a
b0 .
b0 W
b0 `
18
#3075000
08
#3100000
0R
18
#3125000
08
#3150000
18
#3175000
08
#3200000
18
#3220000
1:
#3225000
08
#3250000
0,
1!
b0 p
b0 q
1-
18
#3275000
08
#3300000
1h
1g
18
#3325000
08
#3350000
0!
1i
18
#3375000
08
#3400000
0h
0g
18
#3420000
0:
#3425000
08
#3450000
0-
0i
18
#3475000
08
#3500000
18
#3525000
08
#3550000
18
#3575000
08
#3600000
18
#3625000
08
#3650000
18
#3675000
08
#3700000
18
#3725000
08
#3750000
18
#3775000
08
#3800000
18
#3825000
08
#3850000
18
#3875000
08
#3900000
18
#3920000
b1111 ;
b1111 H
b11001100110011001100110011001100 9
b11001100110011001100110011001100 G
#3925000
08
#3950000
1,
1R
b1111 +
b1111 X
b1111 a
b11001100110011001100110011001100 .
b11001100110011001100110011001100 W
b11001100110011001100110011001100 `
18
#3975000
08
#4000000
0R
18
#4020000
1:
#4025000
08
#4050000
0,
1!
b11001100110011001100110011001100 p
b1111 q
1-
18
#4075000
08
#4100000
1h
1g
18
#4125000
08
#4150000
0!
1i
18
#4175000
08
#4200000
0h
0g
18
#4225000
08
#4250000
0i
18
#4275000
08
#4300000
18
#4325000
08
#4350000
18
#4375000
08
#4400000
18
#4425000
08
#4450000
18
#4475000
08
#4500000
18
#4520000
0:
#4525000
08
#4550000
0-
18
