AXI4_Lite/priority_arbiter3X3.v
module PriorityArbiter_3to3 (
  input [2:0] request,
  output reg [2:0] grants
);

  always @(request) begin
    casex (request)
      3'bXX1: grants = 3'b001; // Priority 1
      3'bX10: grants = 3'b010; // Priority 2
      3'b100: grants = 3'b100; // Priority 3
      default: grants = 3'b000; // No request or invalid request, no grants
    endcase
  end

endmodule

AXI4_Lite/priority_arbiter3X3_tb.v
`timescale 1ns/1ns
`include"priority_arbiter3X3.v"
module Testbench_PriorityArbiter_3to3;
    initial begin
        $dumpfile("priority_arbiter3X3_tb.vcd");
        $dumpvars(0, Testbench_PriorityArbiter_3to3); 
    end

  // Parameters
  parameter PERIOD = 10;

  // Inputs
  reg [2:0] request;
  
  // Outputs
  wire [2:0] grants;

  // Instantiate the PriorityArbiter_3to3 module
  PriorityArbiter_3to3 uut (
    .request(request),
    .grants(grants)
  );

  // Clock generation
  reg clk = 0;
  always #((PERIOD)/2) clk = ~clk;

  // Test stimulus
  initial begin
    // Initialize inputs
    request = 3'b000;

    // Apply stimulus
    #10 request = 3'b001; // Priority 1
    #10 request = 3'b010; // Priority 2
    #10 request = 3'b011; // Priority 3
    #10 request = 3'b100; // Priority 1
    #10 request = 3'b101; // Priority 2
    #10 request = 3'b110; // Priority 3
    #10 request = 3'b111; // Priority 1


    // No request or invalid request
    #10 request = 3'b000;

    #10 $finish;
  end

  // Display output
  always @(posedge clk) begin
    $display("Time=%t request=%b winner=%b", $time, request, grants);
  end

endmodule

AXI4_Lite/priority_arbiter3X3_tb.vcd
$date
	Tue Dec  5 17:46:17 2023
$end
$version
	Icarus Verilog
$end
$timescale
	1ns
$end
$scope module Testbench_PriorityArbiter_3to3 $end
$var wire 3 ! grants [2:0] $end
$var reg 1 " clk $end
$var reg 3 # request [2:0] $end
$scope module uut $end
$var wire 3 $ request [2:0] $end
$var reg 3 % grants [2:0] $end
$upscope $end
$upscope $end
$enddefinitions $end
#0
$dumpvars
b0 %
b0 $
b0 #
0"
b0 !
$end
#5
1"
#10
b1 !
b1 %
0"
b1 #
b1 $
#15
1"
#20
b10 !
b10 %
0"
b10 #
b10 $
#25
1"
#30
b1 !
b1 %
0"
b11 #
b11 $
#35
1"
#40
b100 !
b100 %
0"
b100 #
b100 $
#45
1"
#50
b1 !
b1 %
0"
b101 #
b101 $
#55
1"
#60
b10 !
b10 %
0"
b110 #
b110 $
#65
1"
#70
b1 !
b1 %
0"
b111 #
b111 $
#75
1"
#80
b0 !
b0 %
0"
b0 #
b0 $
