AXI4_Lite/priority_encoder4X2.v
module BinaryEncoder_4to2 (
  input wire [3:0] binary_input,
  output reg [1:0] encoded_output
);


always @ (binary_input) begin
    casex(binary_input)
        4'b1XXX: encoded_output = 2'b11; // Highest priority input A
        4'b01XX: encoded_output = 2'b10; // Second priority input B
        4'b001X: encoded_output = 2'b01; // Third priority input C
        4'b0001: encoded_output = 2'b00; // Lowest priority input D
    endcase
end

endmodule

AXI4_Lite/priority_encoder4X2_tb.v
`timescale 1ns / 1ps
`include"priority_encoder4X2.v"
module Testbench_BinaryEncoder_4to2;
    initial begin
        $dumpfile("priority_encoder4X2_tb.vcd");
        $dumpvars(0, Testbench_BinaryEncoder_4to2); 
    end
  // Parameters
  parameter PERIOD = 10;

  // Inputs
  reg [3:0] binary_input;
  
  // Outputs
  wire [1:0] encoded_output;

  // Instantiate the BinaryEncoder_4to2 module
  BinaryEncoder_4to2 uut (
    .binary_input(binary_input),
    .encoded_output(encoded_output)
  );

  // Clock generation
  reg clk = 0;
  always #((PERIOD)/2) clk = ~clk;

  // Test stimulus
  initial begin
    // Initialize inputs
    binary_input = 4'b0000;

    // Apply stimulus
    #10 binary_input = 4'b0001;
    #10 binary_input = 4'b0010;
    #10 binary_input = 4'b0100;
    #10 binary_input = 4'b1000;

    #10 binary_input = 4'b1010;
    #10 binary_input = 4'b0110;
    #10 binary_input = 4'b1100;
    #10 binary_input = 4'b1111;

    #10 $finish;
  end

  // Display output
  always @(posedge clk) begin
    $display("Time=%t binary_input=%b encoded_output=%b", $time, binary_input, encoded_output);
  end

endmodule

AXI4_Lite/priority_encoder4X2_tb.vcd
$date
	Tue Dec  5 17:41:22 2023
$end
$version
	Icarus Verilog
$end
$timescale
	1ps
$end
$scope module Testbench_BinaryEncoder_4to2 $end
$var wire 2 ! encoded_output [1:0] $end
$var reg 4 " binary_input [3:0] $end
$var reg 1 # clk $end
$scope module uut $end
$var wire 4 $ binary_input [3:0] $end
$var reg 2 % encoded_output [1:0] $end
$upscope $end
$upscope $end
$enddefinitions $end
#0
$dumpvars
bx %
b0 $
0#
b0 "
bx !
$end
#5000
1#
#10000
b0 !
b0 %
0#
b1 "
b1 $
#15000
1#
#20000
b1 !
b1 %
0#
b10 "
b10 $
#25000
1#
#30000
b10 !
b10 %
0#
b100 "
b100 $
#35000
1#
#40000
b11 !
b11 %
0#
b1000 "
b1000 $
#45000
1#
#50000
0#
b1010 "
b1010 $
#55000
1#
#60000
b10 !
b10 %
0#
b110 "
b110 $
#65000
1#
#70000
b11 !
b11 %
0#
b1100 "
b1100 $
#75000
1#
#80000
0#
b1111 "
b1111 $
