handshakes/H_slave.v
module Handshake_slave(
 input clk,
 input rst, 
 input valid, 
 input ready_in,
 input  wire [7:0] data_in,
 output reg ready_out
);
  reg reset =  0;
  reg  [7:0] data;

always @(posedge clk) begin
    if (rst)
        reset <= 1;
    else
    begin
        reset <= 0;
        ready_out <= ready_in;
    end
end

always @(*)begin
    if (reset)begin
        data = 0;
        ready_out = 0;
    end
    if (ready_out && valid)
        data = data_in;
    else
        data = data;
end   
endmodule

handshakes/H_master.v

module Handshake_master(
 input clk , rst , ready_inp,
 input   wire [7:0] data_in,
 output  reg [7:0] data,
 output  reg valid  
);
  reg reset = 0;
  reg dataChanged = 0;
  reg [7:0]  prevData ;

always @(posedge clk) begin
    if (rst)begin
        reset <= 1;
        data <= 0;
    end
    else
    begin
        reset <= 0;
        data <= data_in;
         if (data_in != data) begin
            dataChanged <= 1'b1;
      end else begin
            dataChanged <= 1'b0;
      end
      prevData <= data;
    end
    end

always @(*)begin
    if (reset)
        valid = 0;
    if (dataChanged)
        valid = 1;
        else
    if (ready_inp == 1 && dataChanged == 0)
        valid = 0 ;  
        else
        valid = valid;      
end 
endmodule

AXI4_Lite/round_robin_arbiter.v
`timescale 1ns / 1ps

module round_robin_arbiter(
    
    input [7:0] data_input,
    input ready_input,
    output reg [7:0] data_output,
    output reg ready_output,
    input [7:0] address_of_register,
    input clk, 
    input wire rst,
    // // round robin
    input [1:0] req_sigs,
    output reg [1:0] grant_sigs,

     // handshaking for master1 
      output reg  out_ready_m1,  
      input   [7:0] in_data_m1,
      input    wire in_valid_m1,
     // handshaking for salve1 
      output reg   [7:0] out_data_s1,
      output reg     out_valid_s1,
      input wire in_ready_s1,


     // handshaking for master2 
      output reg  out_ready_m2,  
      input   [7:0] in_data_m2,
      input    wire in_valid_m2,
     // handshaking for slave2 
      output reg   [7:0] out_data_s2,
      output reg     out_valid_s2,
      input wire    in_ready_s2


     );

reg [1:0] curr_state = 0; 
reg [1:0] next_state;
reg [7:0] slave_address_1 = 8'hAA;
reg [7:0] slave_address_2 = 8'hBB;

parameter [1:0] IDLE = 3'b00;
parameter [1:0] STATE_0 = 3'b01;
parameter [1:0] STATE_1 = 3'b10;


always @(posedge clk or posedge rst) begin
  if(rst)
    curr_state <= IDLE;
  else 
    curr_state <= next_state;
end

always @(*) begin
  
  case(curr_state)

    IDLE: begin
            if(req_sigs[0])
              next_state = STATE_0;
            else if(req_sigs[1])
              next_state = STATE_1;  
            else
              next_state = IDLE;
          end

    STATE_0: begin
               if(req_sigs[1])
                 next_state = STATE_1;  
               else if(req_sigs[0])
                 next_state = STATE_0;
               else
                 next_state = IDLE;
             end

    STATE_1: begin
            if(req_sigs[0])
              next_state = STATE_0;
            else if(req_sigs[1])
              next_state = STATE_1;  
            else
              next_state = IDLE;
          end

   default: begin
             if(req_sigs[0])
               next_state = STATE_0;
             else if(req_sigs[1])
               next_state = STATE_1;
             else
               next_state = IDLE;
           end

  endcase
end

always @(*) begin
  
  case(curr_state)

  IDLE : begin
      grant_sigs = 2'b00;
      out_valid_s2   = 0;
      out_data_s2    = 0;
      out_ready_m2   = 0;
      out_valid_s1   = 0;
      out_data_s1    = 0;
      out_ready_m1   = 0;
      data_output    = 0;
      ready_output   = 0;
  end
  

    
    STATE_0 : begin
        grant_sigs = 2'b01; // master1
      
        if (address_of_register == slave_address_1)begin // master1 to slave1
       out_ready_m1   =  in_ready_s1;
       out_data_s1    =  in_data_m1;
       out_valid_s1   =  in_valid_m1;
       data_output = data_input;
       ready_output = ready_input;
        end
    

        else if (address_of_register == slave_address_2) begin // master1 with slave 2
       out_ready_m1   =  in_ready_s2;
       out_data_s2    =  in_data_m1;
       out_valid_s2   =  in_valid_m1;
       data_output = data_input;
       ready_output = ready_input;
        end
        end

    STATE_1 : begin
    grant_sigs = 2'b10; 
     if (address_of_register == slave_address_1)begin // master1 to slave1
       out_ready_m2   =  in_ready_s1;
       out_data_s1    =  in_data_m2;
       out_valid_s1   =  in_valid_m2;
       data_output = data_input;
       ready_output = ready_input;
        end
    

        else if (address_of_register == slave_address_2) begin // master1 with slave 2
       out_ready_m2   =  in_ready_s2;
       out_data_s2    =  in_data_m2;
       out_valid_s2   =  in_valid_m2;
       data_output = data_input;
       ready_output = ready_input; 
        end
        end

    default : begin 
       grant_sigs = 2'b00;
      out_valid_s2 = out_valid_s2;
      out_data_s2 = out_data_s2;
      out_ready_m2 = out_ready_m2;
      out_valid_s1 = out_valid_s1;
      out_data_s1 = out_data_s1;
      out_ready_m1 = out_ready_m1;
      data_output = data_output;
      ready_output = ready_output;
    end 
    
  endcase
end


endmodule

AXI4_Lite/round_robin_arbiter_tb.v
`include "round_robin_arbiter.v"
`include"H_master.v"
`include"H_slave.v"

`timescale 1ns / 1ps

module round_robin_arbiter_tb();

   reg clk;                 // Clock input
   reg rst;
   reg ready_input;
   reg [7:0] data_in;
   wire [7:0] data_wire;
   wire ready_wire;

   // master 1 
   wire [7:0] data_m1_m_to_a;
   wire valid_m1_m_to_a;
   wire ready_m1_m_to_a;

   // slave 1
   wire [7:0] data_s1_a_to_s;
   wire valid_s1_a_to_s;
   wire ready_s1_a_to_s;

   // master 2 
   wire [7:0] data_m2_m_to_a;
   wire valid_m2_m_to_a;
   wire ready_m2_m_to_a;

   // slave 2
   wire [7:0] data_s2_a_to_s;
   wire valid_s2_a_to_s;
   wire ready_s2_a_to_s;


reg [7:0] address_of_register_input;
reg [1:0] req_sigs;
wire [1:0] grant_sigs; 



 initial begin
        $dumpfile("round_robin_arbiter_tb.vcd");
        $dumpvars(0, round_robin_arbiter_tb); 
    end


round_robin_arbiter round_robin_arbiter (
    .clk(clk),
    .rst(rst),
    .grant_sigs(grant_sigs),
    .req_sigs(req_sigs), 
    .address_of_register(address_of_register_input),
    .data_input(data_in),
    .ready_input(ready_input),
    .data_output(data_wire),
    .ready_output(ready_wire),
      //m1
      .out_ready_m1(ready_m1_m_to_a),
      .in_data_m1(data_m1_m_to_a),
      .in_valid_m1(valid_m1_m_to_a),
      // s1
      .in_ready_s1(ready_s1_a_to_s),
      .out_data_s1(data_s1_a_to_s),
      .out_valid_s1(valid_s1_a_to_s),
        //m2
      .out_ready_m2(ready_m2_m_to_a),
      .in_data_m2(data_m2_m_to_a),
      .in_valid_m2(valid_m2_m_to_a),
       //s2
      .in_ready_s2(ready_s2_a_to_s),
      .out_data_s2(data_s2_a_to_s),
      .out_valid_s2(valid_s2_a_to_s)
);

  
Handshake_master dut_Handshake_master_1 (
    .clk(clk),
    .rst(rst),
    .data_in(data_wire),
    .valid(valid_m1_m_to_a),
    .ready_inp(ready_m1_m_to_a),
    .data(data_m1_m_to_a)
);
Handshake_master dut_Handshake_master_2 (
    .clk(clk),
    .rst(rst),
    .data_in(data_wire),
    .valid(valid_m2_m_to_a),
    .ready_inp(ready_m2_m_to_a),
    .data(data_m2_m_to_a)
);
Handshake_slave  dut_Handshake_slave_1 (
    .clk(clk),
    .rst(rst),
    .ready_in(ready_wire),
    .data_in(data_s1_a_to_s),
    .ready_out(ready_s1_a_to_s),
    .valid(valid_s1_a_to_s)
);
Handshake_slave  dut_Handshake_slave_2 (
    .clk(clk),
    .rst(rst),
    .ready_in(ready_wire),
    .data_in(data_s2_a_to_s),
    .ready_out(ready_s2_a_to_s),
    .valid(valid_s2_a_to_s)
);


always #5 clk = ~clk;

initial begin
  clk = 1;
  req_sigs = 2'b00;
  data_in = 8'h00;

  #1000;
   req_sigs = 2'b01;
   address_of_register_input = 8'hAA;
    ready_input = 0;
    rst = 1;
    data_in = 8'hAA;
    #10;
    rst = 0;
    ready_input = 1;
    #100;
    data_in = 8'hBB;
    #100;
    data_in = 8'hCC;
    #200;
   address_of_register_input = 8'hBB;
    data_in = 8'hDD;
    #100;
    data_in = 8'hEE;
    #100;
    data_in = 8'hFF;
   #300;

  req_sigs = 2'b10;
   address_of_register_input = 8'hAA;

    data_in = 8'hFF;
    #100;
    data_in = 8'hEE;
    #100;
    data_in = 8'hDD;
    #200;
   address_of_register_input = 8'hBB;
    data_in = 8'hCC;
    #100;
    data_in = 8'hBB;
    #100;
    data_in = 8'hAA;
   #300;

  address_of_register_input = 8'hAA;
  req_sigs = 2'b11;
    data_in = 8'h55;
    #100;
    data_in = 8'h66;
    #100;
    data_in = 8'h77;
    #200;
    data_in = 8'h88;
    #100;
    data_in = 8'h99;
  #20000;
  $finish;
end

initial begin
  $monitor("req_sigs = %b, grant_sigs = %b", req_sigs, grant_sigs);
end
    endmodule

AXI4_Lite/round_robin_arbiter_tb.vcd
$date
	Sun Dec 10 03:38:35 2023
$end
$version
	Icarus Verilog
$end
$timescale
	1ps
$end
$scope module round_robin_arbiter_tb $end
$var wire 1 ! valid_s2_a_to_s $end
$var wire 1 " valid_s1_a_to_s $end
$var wire 1 # valid_m2_m_to_a $end
$var wire 1 $ valid_m1_m_to_a $end
$var wire 1 % ready_wire $end
$var wire 1 & ready_s2_a_to_s $end
$var wire 1 ' ready_s1_a_to_s $end
$var wire 1 ( ready_m2_m_to_a $end
$var wire 1 ) ready_m1_m_to_a $end
$var wire 2 * grant_sigs [1:0] $end
$var wire 8 + data_wire [7:0] $end
$var wire 8 , data_s2_a_to_s [7:0] $end
$var wire 8 - data_s1_a_to_s [7:0] $end
$var wire 8 . data_m2_m_to_a [7:0] $end
$var wire 8 / data_m1_m_to_a [7:0] $end
$var reg 8 0 address_of_register_input [7:0] $end
$var reg 1 1 clk $end
$var reg 8 2 data_in [7:0] $end
$var reg 1 3 ready_input $end
$var reg 2 4 req_sigs [1:0] $end
$var reg 1 5 rst $end
$scope module dut_Handshake_master_1 $end
$var wire 1 1 clk $end
$var wire 1 5 rst $end
$var wire 1 ) ready_inp $end
$var wire 8 6 data_in [7:0] $end
$var reg 8 7 data [7:0] $end
$var reg 1 8 dataChanged $end
$var reg 8 9 prevData [7:0] $end
$var reg 1 : reset $end
$var reg 1 $ valid $end
$upscope $end
$scope module dut_Handshake_master_2 $end
$var wire 1 1 clk $end
$var wire 1 5 rst $end
$var wire 1 ( ready_inp $end
$var wire 8 ; data_in [7:0] $end
$var reg 8 < data [7:0] $end
$var reg 1 = dataChanged $end
$var reg 8 > prevData [7:0] $end
$var reg 1 ? reset $end
$var reg 1 # valid $end
$upscope $end
$scope module dut_Handshake_slave_1 $end
$var wire 1 1 clk $end
$var wire 1 5 rst $end
$var wire 1 " valid $end
$var wire 1 % ready_in $end
$var wire 8 @ data_in [7:0] $end
$var reg 8 A data [7:0] $end
$var reg 1 ' ready_out $end
$var reg 1 B reset $end
$upscope $end
$scope module dut_Handshake_slave_2 $end
$var wire 1 1 clk $end
$var wire 1 5 rst $end
$var wire 1 ! valid $end
$var wire 1 % ready_in $end
$var wire 8 C data_in [7:0] $end
$var reg 8 D data [7:0] $end
$var reg 1 & ready_out $end
$var reg 1 E reset $end
$upscope $end
$scope module round_robin_arbiter $end
$var wire 8 F address_of_register [7:0] $end
$var wire 1 1 clk $end
$var wire 8 G data_input [7:0] $end
$var wire 8 H in_data_m1 [7:0] $end
$var wire 8 I in_data_m2 [7:0] $end
$var wire 1 ' in_ready_s1 $end
$var wire 1 & in_ready_s2 $end
$var wire 1 $ in_valid_m1 $end
$var wire 1 # in_valid_m2 $end
$var wire 1 3 ready_input $end
$var wire 2 J req_sigs [1:0] $end
$var wire 1 5 rst $end
$var reg 2 K curr_state [1:0] $end
$var reg 8 L data_output [7:0] $end
$var reg 2 M grant_sigs [1:0] $end
$var reg 2 N next_state [1:0] $end
$var reg 8 O out_data_s1 [7:0] $end
$var reg 8 P out_data_s2 [7:0] $end
$var reg 1 ) out_ready_m1 $end
$var reg 1 ( out_ready_m2 $end
$var reg 1 " out_valid_s1 $end
$var reg 1 ! out_valid_s2 $end
$var reg 1 % ready_output $end
$var reg 8 Q slave_address_1 [7:0] $end
$var reg 8 R slave_address_2 [7:0] $end
$upscope $end
$upscope $end
$enddefinitions $end
#0
$dumpvars
b10111011 R
b10101010 Q
b0 P
b0 O
b0 N
b0 M
b0 L
b0 K
b0 J
b0 I
b0 H
b0 G
bx F
0E
bx D
b0 C
0B
bx A
b0 @
0?
bx >
0=
b0 <
b0 ;
0:
bx 9
08
b0 7
b0 6
x5
b0 4
x3
b0 2
11
bx 0
b0 /
b0 .
b0 -
b0 ,
b0 +
b0 *
0)
0(
0'
0&
0%
x$
x#
0"
0!
$end
#5000
01
#10000
b0 >
b0 9
11
#15000
01
#20000
11
#25000
01
#30000
11
#35000
01
#40000
11
#45000
01
#50000
11
#55000
01
#60000
11
#65000
01
#70000
11
#75000
01
#80000
11
#85000
01
#90000
11
#95000
01
#100000
11
#105000
01
#110000
11
#115000
01
#120000
11
#125000
01
#130000
11
#135000
01
#140000
11
#145000
01
#150000
11
#155000
01
#160000
11
#165000
01
#170000
11
#175000
01
#180000
11
#185000
01
#190000
11
#195000
01
#200000
11
#205000
01
#210000
11
#215000
01
#220000
11
#225000
01
#230000
11
#235000
01
#240000
11
#245000
01
#250000
11
#255000
01
#260000
11
#265000
01
#270000
11
#275000
01
#280000
11
#285000
01
#290000
11
#295000
01
#300000
11
#305000
01
#310000
11
#315000
01
#320000
11
#325000
01
#330000
11
#335000
01
#340000
11
#345000
01
#350000
11
#355000
01
#360000
11
#365000
01
#370000
11
#375000
01
#380000
11
#385000
01
#390000
11
#395000
01
#400000
11
#405000
01
#410000
11
#415000
01
#420000
11
#425000
01
#430000
11
#435000
01
#440000
11
#445000
01
#450000
11
#455000
01
#460000
11
#465000
01
#470000
11
#475000
01
#480000
11
#485000
01
#490000
11
#495000
01
#500000
11
#505000
01
#510000
11
#515000
01
#520000
11
#525000
01
#530000
11
#535000
01
#540000
11
#545000
01
#550000
11
#555000
01
#560000
11
#565000
01
#570000
11
#575000
01
#580000
11
#585000
01
#590000
11
#595000
01
#600000
11
#605000
01
#610000
11
#615000
01
#620000
11
#625000
01
#630000
11
#635000
01
#640000
11
#645000
01
#650000
11
#655000
01
#660000
11
#665000
01
#670000
11
#675000
01
#680000
11
#685000
01
#690000
11
#695000
01
#700000
11
#705000
01
#710000
11
#715000
01
#720000
11
#725000
01
#730000
11
#735000
01
#740000
11
#745000
01
#750000
11
#755000
01
#760000
11
#765000
01
#770000
11
#775000
01
#780000
11
#785000
01
#790000
11
#795000
01
#800000
11
#805000
01
#810000
11
#815000
01
#820000
11
#825000
01
#830000
11
#835000
01
#840000
11
#845000
01
#850000
11
#855000
01
#860000
11
#865000
01
#870000
11
#875000
01
#880000
11
#885000
01
#890000
11
#895000
01
#900000
11
#905000
01
#910000
11
#915000
01
#920000
11
#925000
01
#930000
11
#935000
01
#940000
11
#945000
01
#950000
11
#955000
01
#960000
11
#965000
01
#970000
11
#975000
01
#980000
11
#985000
01
#990000
11
#995000
01
#1000000
0$
0#
b0 A
b0 D
1:
1?
1B
1E
b1 N
11
b10101010 2
b10101010 G
15
03
b10101010 0
b10101010 F
b1 4
b1 J
#1005000
01
#1010000
1%
b10101010 +
b10101010 6
b10101010 ;
b10101010 L
b1 *
b1 M
0E
0B
0?
0:
b1 K
11
13
05
#1015000
01
#1020000
b10101010 A
1"
1$
1#
b10101010 -
b10101010 @
b10101010 O
1)
18
b10101010 /
b10101010 7
b10101010 H
1=
b10101010 .
b10101010 <
b10101010 I
1'
1&
11
#1025000
01
#1030000
0"
0$
b10101010 >
0=
b10101010 9
08
11
#1035000
01
#1040000
11
#1045000
01
#1050000
11
#1055000
01
#1060000
11
#1065000
01
#1070000
11
#1075000
01
#1080000
11
#1085000
01
#1090000
11
#1095000
01
#1100000
11
#1105000
01
#1110000
b10111011 A
1"
1$
b10111011 -
b10111011 @
b10111011 O
1=
b10111011 .
b10111011 <
b10111011 I
18
b10111011 /
b10111011 7
b10111011 H
b10111011 +
b10111011 6
b10111011 ;
b10111011 L
11
b10111011 2
b10111011 G
#1115000
01
#1120000
0"
0$
b10111011 9
08
b10111011 >
0=
11
#1125000
01
#1130000
11
#1135000
01
#1140000
11
#1145000
01
#1150000
11
#1155000
01
#1160000
11
#1165000
01
#1170000
11
#1175000
01
#1180000
11
#1185000
01
#1190000
11
#1195000
01
#1200000
11
#1205000
01
#1210000
b11001100 A
1"
1$
b11001100 -
b11001100 @
b11001100 O
1=
b11001100 .
b11001100 <
b11001100 I
18
b11001100 /
b11001100 7
b11001100 H
b11001100 +
b11001100 6
b11001100 ;
b11001100 L
11
b11001100 2
b11001100 G
#1215000
01
#1220000
0"
0$
b11001100 9
08
b11001100 >
0=
11
#1225000
01
#1230000
11
#1235000
01
#1240000
11
#1245000
01
#1250000
11
#1255000
01
#1260000
11
#1265000
01
#1270000
11
#1275000
01
#1280000
11
#1285000
01
#1290000
11
#1295000
01
#1300000
11
#1305000
01
#1310000
11
#1315000
01
#1320000
11
#1325000
01
#1330000
11
#1335000
01
#1340000
11
#1345000
01
#1350000
11
#1355000
01
#1360000
11
#1365000
01
#1370000
11
#1375000
01
#1380000
11
#1385000
01
#1390000
11
#1395000
01
#1400000
11
#1405000
01
#1410000
b11011101 D
1!
1$
1=
b11011101 .
b11011101 <
b11011101 I
18
b11011101 /
b11011101 7
b11011101 H
b11011101 +
b11011101 6
b11011101 ;
b11011101 L
b11011101 ,
b11011101 C
b11011101 P
11
b11011101 2
b11011101 G
b10111011 0
b10111011 F
#1415000
01
#1420000
0!
0$
b11011101 9
08
b11011101 >
0=
11
#1425000
01
#1430000
11
#1435000
01
#1440000
11
#1445000
01
#1450000
11
#1455000
01
#1460000
11
#1465000
01
#1470000
11
#1475000
01
#1480000
11
#1485000
01
#1490000
11
#1495000
01
#1500000
11
#1505000
01
#1510000
b11101110 D
1!
1$
b11101110 ,
b11101110 C
b11101110 P
1=
b11101110 .
b11101110 <
b11101110 I
18
b11101110 /
b11101110 7
b11101110 H
b11101110 +
b11101110 6
b11101110 ;
b11101110 L
11
b11101110 2
b11101110 G
#1515000
01
#1520000
0!
0$
b11101110 9
08
b11101110 >
0=
11
#1525000
01
#1530000
11
#1535000
01
#1540000
11
#1545000
01
#1550000
11
#1555000
01
#1560000
11
#1565000
01
#1570000
11
#1575000
01
#1580000
11
#1585000
01
#1590000
11
#1595000
01
#1600000
11
#1605000
01
#1610000
b11111111 D
1!
1$
b11111111 ,
b11111111 C
b11111111 P
1=
b11111111 .
b11111111 <
b11111111 I
18
b11111111 /
b11111111 7
b11111111 H
b11111111 +
b11111111 6
b11111111 ;
b11111111 L
11
b11111111 2
b11111111 G
#1615000
01
#1620000
0!
0$
b11111111 9
08
b11111111 >
0=
11
