AXI4_Lite/RRArbiter.v
module round_robin_arbiter (
	rst_an,
	clk,
	req,
	grant
);


input		rst_an;
input		clk;
input	[3:0]	req;
output	[3:0]	grant;

reg	 [3:0]	    rotate_ptr;
wire [3:0]	mask_req;
reg	 [3:0]	    mask_grant;
wire [3:0]	grant_comb;
reg	 [3:0]	    grant;
wire		    no_mask_req;
reg	 [3:0]	    nomask_grant;

always @ (posedge clk or negedge rst_an)
begin
	if (!rst_an)
		rotate_ptr[3:0] <= 4'b1111;
	else 
		case (1'b1) 
            // synthesis parallel_case
			grant[0]: rotate_ptr[3:0] <= 4'b1110;
			grant[1]: rotate_ptr[3:0] <= 4'b1100;
			grant[2]: rotate_ptr[3:0] <= 4'b1000;
			grant[3]: rotate_ptr[3:0] <= 4'b1111;
		endcase 
end

assign mask_req[3:0] = req[3:0] & rotate_ptr[3:0];

// simple priority arbiter for mask req
always @ (*)
begin
	mask_grant[3:0] = 4'b0;
	if (mask_req[0])	mask_grant[0] = 1'b1;
	else if (mask_req[1])	mask_grant[1] = 1'b1;
	else if (mask_req[2])	mask_grant[2] = 1'b1;
	else if (mask_req[3])	mask_grant[3] = 1'b1;
end

// simple priority arbiter for no mask req
always @ (*)
begin
	nomask_grant[3:0] = 4'b0;
	if (req[0])		nomask_grant[0] = 1'b1;
	else if (req[1])	nomask_grant[1] = 1'b1;
	else if (req[2])	nomask_grant[2] = 1'b1;
	else if (req[3])	nomask_grant[3] = 1'b1;
end

assign no_mask_req = ~|mask_req[3:0];
//assign grant_comb[3:0] = no_mask_req ? nomask_grant[3:0] : mask_grant[3:0];
assign grant_comb[3:0] = (nomask_grant[3:0] & {4{no_mask_req}}) | mask_grant[3:0];

always @ (posedge clk or negedge rst_an)
begin
	if (!rst_an)	grant[3:0] <= 4'b0;
	else		grant[3:0] <= grant_comb[3:0] & ~grant[3:0];
end
endmodule

AXI4_Lite/RRArbiter_tb.v
`timescale 1ns/1ns
`include"RRArbiter.v"
module tb();


reg clk;
reg req0;
reg req1;
reg req2;
reg req3;
reg rst_an;

round_robin_arbiter dut (
	.req({req3,req2,req1,req0}),
	.grant({grant3,grant2,grant1,grant0}),
	.clk(clk),
	.rst_an(rst_an)
);

    initial begin
        $dumpfile("RRArbiter_tb.vcd");
        $dumpvars(0, tb); 
    end

initial
begin
	clk = 0;
	req3 = 0;
	req2 = 0;
	req1 = 0;
	req0 = 0;
	rst_an = 1'b1;
	#10 rst_an = 0;
	#10 rst_an = 1;
	repeat (1) @ (posedge clk);
    	req3 <= 0;
    req2 <= 0;
req1 <= 0;
req0 <= 0;
    #20
	req3 <= 0;
    req2 <= 1;
req1 <= 1;
req0 <= 0;
	// repeat (1) @ (posedge clk);
	// req2 <= 1;
	// req1 <= 0;
	// repeat (1) @ (posedge clk);
	// req3 <= 1;
	// req2 <= 0;
	// repeat (1) @ (posedge clk);
	// req3 <= 0;
	// repeat (1) @ (posedge clk);
	// req0 <= 0;
	// repeat (1) @ (posedge clk);
	#100  $finish;

end

always	#1 clk = ~clk;
endmodule

AXI4_Lite/RRArbiter_tb.vcd
$date
	Wed Dec  6 19:26:25 2023
$end
$version
	Icarus Verilog
$end
$timescale
	1ns
$end
$scope module tb $end
$var wire 1 ! grant3 $end
$var wire 1 " grant2 $end
$var wire 1 # grant1 $end
$var wire 1 $ grant0 $end
$var reg 1 % clk $end
$var reg 1 & req0 $end
$var reg 1 ' req1 $end
$var reg 1 ( req2 $end
$var reg 1 ) req3 $end
$var reg 1 * rst_an $end
$scope module dut $end
$var wire 1 % clk $end
$var wire 4 + grant_comb [3:0] $end
$var wire 4 , mask_req [3:0] $end
$var wire 4 - req [3:0] $end
$var wire 1 * rst_an $end
$var wire 1 . no_mask_req $end
$var reg 4 / grant [3:0] $end
$var reg 4 0 mask_grant [3:0] $end
$var reg 4 1 nomask_grant [3:0] $end
$var reg 4 2 rotate_ptr [3:0] $end
$upscope $end
$upscope $end
$enddefinitions $end
#0
$dumpvars
bx 2
b0 1
b0 0
bx /
1.
b0 -
b0 ,
b0 +
1*
0)
0(
0'
0&
0%
x$
x#
x"
x!
$end
#1
0$
0#
0"
0!
b0 /
1%
#2
0%
#3
1%
#4
0%
#5
1%
#6
0%
#7
1%
#8
0%
#9
1%
#10
b1111 2
0%
0*
#11
1%
#12
0%
#13
1%
#14
0%
#15
1%
#16
0%
#17
1%
#18
0%
#19
1%
#20
0%
1*
#21
1%
#22
0%
#23
1%
#24
0%
#25
1%
#26
0%
#27
1%
#28
0%
#29
1%
#30
0%
#31
1%
#32
0%
#33
1%
#34
0%
#35
1%
#36
0%
#37
1%
#38
0%
#39
1%
#40
0%
#41
b10 +
b10 0
0.
b110 ,
b10 1
1'
b110 -
1(
1%
#42
0%
#43
1#
b10 /
1%
#44
0%
#45
b100 +
b100 0
0#
b100 ,
b0 /
b1100 2
1%
#46
0%
#47
1"
b100 /
1%
#48
0%
#49
b10 +
b0 0
0"
1.
b0 ,
b0 /
b1000 2
1%
#50
0%
#51
1#
b10 /
1%
#52
0%
#53
b100 +
b100 0
0#
0.
b100 ,
b0 /
b1100 2
1%
#54
0%
#55
1"
b100 /
1%
#56
0%
#57
b10 +
b0 0
0"
1.
b0 ,
b0 /
b1000 2
1%
#58
0%
#59
1#
b10 /
1%
#60
0%
#61
b100 +
b100 0
0#
0.
b100 ,
b0 /
b1100 2
1%
#62
0%
#63
1"
b100 /
1%
#64
0%
#65
b10 +
b0 0
0"
1.
b0 ,
b0 /
b1000 2
1%
#66
0%
#67
1#
b10 /
1%
#68
0%
#69
b100 +
b100 0
0#
0.
b100 ,
b0 /
b1100 2
1%
#70
0%
#71
1"
b100 /
1%
#72
0%
#73
b10 +
b0 0
0"
1.
b0 ,
b0 /
b1000 2
1%
#74
0%
#75
1#
b10 /
1%
#76
0%
#77
b100 +
b100 0
0#
0.
b100 ,
b0 /
b1100 2
1%
#78
0%
#79
1"
b100 /
1%
#80
0%
#81
b10 +
b0 0
0"
1.
b0 ,
b0 /
b1000 2
1%
#82
0%
#83
1#
b10 /
1%
#84
0%
#85
b100 +
b100 0
0#
0.
b100 ,
b0 /
b1100 2
1%
#86
0%
#87
1"
b100 /
1%
#88
0%
#89
b10 +
b0 0
0"
1.
b0 ,
b0 /
b1000 2
1%
#90
0%
#91
1#
b10 /
1%
#92
0%
#93
b100 +
b100 0
0#
0.
b100 ,
b0 /
b1100 2
1%
#94
0%
#95
1"
b100 /
1%
#96
0%
#97
b10 +
b0 0
0"
1.
b0 ,
b0 /
b1000 2
1%
#98
0%
#99
1#
b10 /
1%
#100
0%
#101
b100 +
b100 0
0#
0.
b100 ,
b0 /
b1100 2
1%
#102
0%
#103
1"
b100 /
1%
#104
0%
#105
b10 +
b0 0
0"
1.
b0 ,
b0 /
b1000 2
1%
#106
0%
#107
1#
b10 /
1%
#108
0%
#109
b100 +
b100 0
0#
0.
b100 ,
b0 /
b1100 2
1%
#110
0%
#111
1"
b100 /
1%
#112
0%
#113
b10 +
b0 0
0"
1.
b0 ,
b0 /
b1000 2
1%
#114
0%
#115
1#
b10 /
1%
#116
0%
#117
b100 +
b100 0
0#
0.
b100 ,
b0 /
b1100 2
1%
#118
0%
#119
1"
b100 /
1%
#120
0%
#121
b10 +
b0 0
0"
1.
b0 ,
b0 /
b1000 2
1%
#122
0%
#123
1#
b10 /
1%
#124
0%
#125
b100 +
b100 0
0#
0.
b100 ,
b0 /
b1100 2
1%
#126
0%
#127
1"
b100 /
1%
#128
0%
#129
b10 +
b0 0
0"
1.
b0 ,
b0 /
b1000 2
1%
#130
0%
#131
1#
b10 /
1%
#132
0%
#133
b100 +
b100 0
0#
0.
b100 ,
b0 /
b1100 2
1%
#134
0%
#135
1"
b100 /
1%
#136
0%
#137
b10 +
b0 0
0"
1.
b0 ,
b0 /
b1000 2
1%
#138
0%
#139
1#
b10 /
1%
#140
0%
#141
b100 +
b100 0
0#
0.
b100 ,
b0 /
b1100 2
1%
