AXI4_Lite/synchronous_muller_C_element.v
module SynchronousMullerCElement (
  input [2:0] data_input,
  input clk,
  output reg  Z
);

  always @(posedge clk) begin
    // Müller C-element behavior
  if (data_input == 3'b111)
     Z = 1;
     else
    if (data_input == 3'b000)
     Z = 0;
     else
      Z = Z;
  end

endmodule

AXI4_Lite/synchronous_muller_C_element_tb.v
`timescale 1ns/1ns
`include"synchronous_muller_C_element.v"
module Testbench_SynchronousMullerCElement;



    initial begin
        $dumpfile("synchronous_muller_C_element_tb.vcd");
        $dumpvars(0, Testbench_SynchronousMullerCElement); 
    end


  // Parameters
  parameter PERIOD = 10;

  // Inputs
  reg [2:0] data_input;
  reg clk;

  // Outputs
  wire  Z;

  // Instantiate the SynchronousMullerCElement module
  SynchronousMullerCElement uut (
    .data_input(data_input),
    .clk(clk),
    .Z(Z)
  );

  // Clock generation
  initial begin
    clk = 1;
    forever #((PERIOD)/2) clk = ~clk;
  end

  // Test stimulus
  initial begin

    // Apply stimulus
    data_input = 3'b000; // Middle bit is 1, output should follow data_input
    #10 data_input = 3'b001; // Least significant bit is 0, output should follow data_input
    #10 data_input = 3'b010; // Most significant bit is 1, output should follow data_input
    #10 data_input = 3'b011; // Least and most significant bits are 1, output should follow middle bit
        // Apply stimulus
    #10 data_input = 3'b100; // Middle bit is 1, output should follow data_input
    #10 data_input = 3'b101; // Least significant bit is 0, output should follow data_input
    #10 data_input = 3'b110; // Most significant bit is 1, output should follow data_input
    #10 data_input = 3'b111; // Least and most significant bits are 1, output should follow middle bit

    #10 data_input = 3'b001; // Least significant bit is 0, output should follow data_input
    #10 data_input = 3'b010; // Most significant bit is 1, output should follow data_input
    #10 data_input = 3'b011; // Least and most significant bits are 1, output should follow middle bit
        // Apply stimulus
    #10 data_input = 3'b100; // Middle bit is 1, output should follow data_input
    #10 data_input = 3'b101; // Least significant bit is 0, output should follow data_input
    #10 data_input = 3'b110; // Most significant bit is 1, output should follow data_input
    data_input = 3'b000; // Middle bit is 1, output should follow data_input
    #300
    data_input = 3'b111; // Middle bit is 1, output should follow data_input
    #1000 $finish;
  end

  // Display output
  always @(posedge clk) begin
    $display("Time=%t data_input=%b Z=%b", $time, data_input, Z);
  end

endmodule

AXI4_Lite/synchronous_muller_C_element_tb.vcd
$date
	Tue Dec  5 18:46:45 2023
$end
$version
	Icarus Verilog
$end
$timescale
	1ns
$end
$scope module Testbench_SynchronousMullerCElement $end
$var wire 1 ! Z $end
$var reg 1 " clk $end
$var reg 3 # data_input [2:0] $end
$scope module uut $end
$var wire 1 " clk $end
$var wire 3 $ data_input [2:0] $end
$var reg 1 ! Z $end
$upscope $end
$upscope $end
$enddefinitions $end
#0
$dumpvars
b0 $
b0 #
1"
0!
$end
#5
0"
#10
1"
b1 #
b1 $
#15
0"
#20
1"
b10 #
b10 $
#25
0"
#30
1"
b11 #
b11 $
#35
0"
#40
1"
b100 #
b100 $
#45
0"
#50
1"
b101 #
b101 $
#55
0"
#60
1"
b110 #
b110 $
#65
0"
#70
1!
1"
b111 #
b111 $
#75
0"
#80
1"
b1 #
b1 $
#85
0"
#90
1"
b10 #
b10 $
#95
0"
#100
1"
b11 #
b11 $
#105
0"
#110
1"
b100 #
b100 $
#115
0"
#120
1"
b101 #
b101 $
#125
0"
#130
0!
1"
b0 #
b0 $
